featureforge_llm/__init__.py
featureforge_llm/core/__init__.py
featureforge_llm/core/pipeline.py
featureforge_llm/core/utils.py
featureforge_llm/data/__init__.py
featureforge_llm/data/data_analyzer.py
featureforge_llm/data/feature_implementer.py
featureforge_llm/executors/__init__.py
featureforge_llm/executors/code_executor.py
featureforge_llm/executors/safety_utils.py
featureforge_llm/llm/__init__.py
featureforge_llm/llm/base.py
featureforge_llm/llm/gemini_provider.py
featureforge_llm/llm/openai_provider.py
featureforge_llm/parsers/__init__.py
featureforge_llm/parsers/code_parser.py
featureforge_llm/parsers/json_parser.py
featureforge_llm-1.0.0.dist-info/METADATA
featureforge_llm-1.0.0.dist-info/WHEEL
featureforge_llm-1.0.0.dist-info/top_level.txt
featureforge_llm-1.0.0.dist-info/RECORD
