Metadata-Version: 2.2
Name: featureforge-llm
Version: 1.0.0
Summary: Automated Feature Engineering Toolkit Based on Large Language Models
Home-page: https://github.com/cgxjdzz/FeatureForge-LLM/
Author: Feifan Zhang
Author-email: Feifan Zhang <cgxjdzz@gmail.com>
License: MIT
Project-URL: Homepage, https://github.com/cgxjdzz/FeatureForge-LLM
Project-URL: Repository, https://github.com/cgxjdzz/FeatureForge-LLM
Project-URL: Issues, https://github.com/cgxjdzz/FeatureForge-LLM/issues
Keywords: feature engineering,LLM,machine learning,AI,automation
Requires-Python: >=3.11
Requires-Dist: numpy>=2.2.4
Requires-Dist: pandas>=2.2.3
Requires-Dist: pydantic>=2.11.0b1
Requires-Dist: pydantic_core>=2.31.1
Requires-Dist: requests>=2.32.3
Requires-Dist: httpx>=0.28.1
Requires-Dist: openai>=1.66.3
Requires-Dist: google-auth>=2.38.0
Requires-Dist: google-genai>=1.5.0
Requires-Dist: tqdm>=4.67.1
Dynamic: author
Dynamic: home-page
Dynamic: requires-python
